Workbook

Sheet Analysis
A1: LBRX QSBS & Evecxia Investment Analysis
A2: Hold LBRX vs. §1045 Rollover to Evecxia — Simplified Scenario Comparison | E2: February 16, 2026
A4: INVESTMENT PARAMETERS
A5: Series B Investment ($) | B5: 100000
A6: Series B Price/Share ($) | B6: 24
A7: Shares Acquired | B7: =B5/B6
A8: Investment Date | B8: 44684
A9: QSBS 5-Year Date | B9: =B8+1826
A11: TAX RATES
A12: Federal LTCG + NIIT Rate | B12: 0.238
A13: State Tax Rate | B13: 0
A14: Combined Tax Rate | B14: =B12+B13
A16: §1045 ROLLOVER TO EVECXIA
A17: LBRX Lock-Up Sale Price | B17: 24.22
A18: LBRX Sale Proceeds (at lock-up) | B18: =B17*B7
A19: Evecxia Share Price (Series A) | B19: 0.1069
A20: Evecxia Shares Acquired | B20: =B18/B19
A21: Evecxia Total Shares at Readout (est.) | B21: 365000000
A22: Investor Ownership % | B22: =B20/B21
A24: SCENARIO COMPARISON
B25: PATH A: HOLD LBRX | D25: PATH B: §1045 → EVECXIA
A26: Metric | B26: Ph3 Positive (Base) | C26: Ph3 Negative (Base) | D26: Ph2 Positive (Base) | E26: Ph2 Negative (Base)
A27: Sale Date | B27: Oct 2027 (post-QSBS) | C27: Oct 2027 (post-QSBS) | D27: Oct 2027 (post-QSBS) | E27: Oct 2027 (post-QSBS)
A28: Sale Price/Share | B28: =Comps!C6 | C28: =Comps!C9 | D28: =Comps!B15/B21 | E28: =Comps!B18/B21
A29: Shares | B29: =B7 | C29: =B7 | D29: =B20 | E29: =B20
A30: Gross Proceeds | B30: =B28*B29 | C30: =C28*C29 | D30: =D28*D29 | E30: =E28*E29
A31: Cost Basis | B31: =B5 | C31: =B5 | D31: =B5 | E31: =B5
A32: Gross Gain | B32: =B30-B31 | C32: =C30-C31 | D32: =D30-D31 | E32: =E30-E31
A33: QSBS 5-Year Met? | B33: YES | C33: YES | D33: YES* | E33: YES*
A34: §1202 Exclusion | B34: =IF(B32>0,MIN(B32,MAX(10000000,10*B31)),0) | C34: =IF(C32>0,MIN(C32,MAX(10000000,10*C31)),0) | D34: =IF(D32>0,MIN(D32,MAX(10000000,10*D31)),0) | E34: =IF(E32>0,MIN(E32,MAX(10000000,10*E31)),0)
A35: Taxable Gain | B35: =MAX(0,B32-B34) | C35: =MAX(0,C32-C34) | D35: =MAX(0,D32-D34) | E35: =MAX(0,E32-E34)
A36: Total Tax | B36: =B35*B14 | C36: =C35*B14 | D36: =D35*B14 | E36: =E35*B14
A37: NET AFTER-TAX | B37: =B30-B36 | C37: =C30-C36 | D37: =D30-D36 | E37: =E30-E36
A38: MOIC | B38: =B37/B31 | C38: =C37/C31 | D38: =D37/D31 | E38: =E37/E31
A39: Effective Tax Rate | B39: =IF(B32>0,B36/B32,0) | C39: =IF(C32>0,C36/C32,0) | D39: =IF(D32>0,D36/D32,0) | E39: =IF(E32>0,E36/E32,0)
A41: PROBABILITY-WEIGHTED DECISION ANALYSIS
A42: P(LBRX Phase 3 Success) | B42: =Comps!B22 | C42: (industry avg: 50-60%)
A43: P(Evecxia Phase 2 Success) | B43: =Comps!B23 | C43: (CNS Phase 2: 30-40%)
A45: Path A Expected Value (Hold LBRX) | B45: =B42*B37+(1-B42)*C37
A46: Path B Expected Value (§1045→Evecxia) | B46: =B43*D37+(1-B43)*E37
A48: ADVANTAGE (Path B - Path A) | B48: =B46-B45
A49: Path B Multiple of Path A | B49: =IF(B45>0,B46/B45,"N/A")
A51: KEY INSIGHTS & RECOMMENDATION
A52: QSBS Timing: 5-year threshold met May 3, 2027. Both Phase 3 (Oct 2027) and Evecxia Phase 2 (Oct 2027) readouts fall AFTER this date → §1202 exclusion available for both paths.
A53: Tax Efficiency: Both paths achieve 0% effective tax rate through §1202 exclusion (gains well under $10M cap). Lock-up sale in March 2026 would NOT qualify → 23.8% tax.
A54: Evecxia Upside: §1045 rollover converts LBRX position into early-stage Evecxia equity at Series A pricing ($0.11/share). At Phase 2 positive base case ($1.5B), this generates ~38x MOIC vs ~4x for LBRX Phase 3 positive.
A55: Downside Protection: Even in Evecxia Ph2 negative scenario ($120M), the ~3x MOIC rivals the LBRX Phase 3 positive base case, while LBRX Phase 3 failure yields ~0.3x (capital loss).
A56: Probability-Weighted: Evecxia pathway expected value exceeds LBRX hold despite lower clinical probability (35% vs 55%) due to magnitude of value inflection at Series A entry.
A57: §1045 Mechanics: Sell LBRX at lock-up → reinvest proceeds into Evecxia QSBS within 60 days → holding period tacks from original Series B date (May 2022) → §1202 exclusion at exit.
A58: *Evecxia QSBS status via §1045 tacking from original Series B holding period.
A60: RECOMMENDATION: §1045 rollover to Evecxia offers superior risk-adjusted expected value. The asymmetric upside at Series A entry pricing more than compensates for Evecxia's lower Phase 2 success probability vs. LBRX Phase 3.
A62: DISCLAIMER: For illustrative and educational purposes only. Consult a qualified CPA or tax attorney before making investment or tax decisions.

Sheet Comps
A1: COMPARABLE VALUATIONS & ASSUMPTIONS
A3: LBRX POST-PHASE 3 SCENARIOS
A4: Scenario | B4: Market Cap | C4: Price/Share | D4: Comparable Basis
A5: Positive - Conservative | B5: 1500000000 | C5: 50 | D5: Comp: ITCI post-Ph3 trajectory ($530M→$850M→$14.6B)
A6: Positive - Base Case | B6: 3000000000 | C6: 100 | D6: Comp: Karuna pre-Ph3 range ($3.0-3.5B)
A7: Positive - Karuna-style | B7: 5000000000 | C7: 165 | D7: Comp: Karuna post-EMERGENT-2 (~$5B)
A8: Negative - Wipeout | B8: 100000000 | C8: 3.3 | D8: Comp: Minerva post-Ph3 failure (~$50-70M)
A9: Negative - Cash Floor | B9: 200000000 | C9: 6.6 | D9: Comp: Cash floor (~$400M cash, discounted for burn)
A10: Negative - Modest Decline | B10: 350000000 | C10: 11.5 | D10: Comp: Modest failure with intact backup pipeline
A12: EVECXIA POST-PHASE 2 SCENARIOS
A13: Scenario | B13: Valuation | C13: Probability | D13: Comparable Basis
A14: Positive - Modest | B14: 800000000 | C14: 0.35 | D14: Comp: Below Karuna Ph2 ($2B) — private discount + smaller market
A15: Positive - Strong (Karuna-like) | B15: 1500000000 | C15: 0.35 | D15: Comp: Karuna Ph2 ($2B) with ~25% discount
A16: Positive - Blowout + M&A | B16: 3000000000 | C16: 0.35 | D16: Comp: Cerevel acquisition ($8.7B) — requires M&A premium
A17: Negative - Wipeout | B17: 50000000 | C17: 0.65 | D17: Floor: cash + minimal residual IP value
A18: Negative - Platform Value | B18: 120000000 | C18: 0.65 | D18: Failed primary but platform/pipeline retains value
A19: Negative - Borderline | B19: 250000000 | C19: 0.65 | D19: Borderline miss — company remains fundable
A21: KEY ASSUMPTIONS
A22: LBRX Phase 3 Success Probability | B22: 0.55
A23: Evecxia Phase 2 Success Probability | B23: 0.35
A24: LBRX Total Shares Outstanding | B24: 30M shares
A25: Evecxia Total Shares at Readout | B25: 365M shares
A26: Evecxia IPO Valuation (2027) | B26: $180M
A27: Lock-Up Price (Mar 2026) | B27: $24.22

Sheet Citations
A1: SOURCES, COMPARABLE TRANSACTIONS & SCENARIO JUSTIFICATION
A3: COMPARABLE CNS/PSYCHIATRY TRANSACTIONS
A4: These transactions anchor the valuation scenarios used in this analysis.
A6: Company / Event | B6: Pre-Event Value | C6: Post-Event Value | D6: Change | E6: Relevance to Model
A7: Karuna (KRTX) — Phase 2 positive Nov 2019, schizophrenia (KarXT) | B7: ~$414M mkt cap | C7: ~$2.0B mkt cap (+380% in 1 day) | D7: +380% | E7: Primary upside comp for Evecxia Ph2+. Novel MOA (muscarinic agonist) drove massive rerating. Evecxia has less novel MOA but targets underserved OCD market.
A8: Karuna (KRTX) — Phase 3 positive Aug 2022 (EMERGENT-2) | B8: ~$3.0-3.5B mkt cap | C8: ~$5.0B+ mkt cap (+64% in 1 day) | D8: +64% | E8: Primary upside comp for LBRX Ph3+. Validates $5B high-end scenario. LBRX LB-102 has differentiated D2/D3/5-HT7 MOA.
A9: Karuna (KRTX) — BMS acquisition Dec 2023, $330/share | B9: ~$9B (pre-rumor) | C9: $14.0B acquisition | D9: +53% premium | E9: Supports M&A premium scenario ($5B high). Post-NDA filing premium; LBRX would need to reach that stage.
A10: Intra-Cellular (ITCI) — Ph3 bipolar+ Jul 2019 (lumateperone) | B10: ~$530M mkt cap | C10: ~$850M mkt cap (+60% in 1 day) | D10: +60% | E10: Supports LBRX Ph3+ $1.5B low-end. ITCI had similar pre-data mkt cap to LBRX's current $613M.
A11: Intra-Cellular (ITCI) — J&J acquisition Jan 2025, $132/share | B11: ~$10.5B mkt cap | C11: $14.6B acquisition | D11: +39% premium | E11: Long-term value comp. ITCI grew from $530M to $14.6B over 5.5 years with two FDA approvals + $681M revenue.
A12: Cerevel (CERE) — AbbVie acquisition Dec 2023, Phase 2 stage | B12: ~$5B mkt cap (pre-rumor) | C12: $8.7B acquisition | D12: +73% premium | E12: Phase 2 acquisition comp. However, lead asset (emraclidine) subsequently FAILED Phase 2 → $3.5B impairment. Cautionary comp.
A13: Cerevel/AbbVie — Emraclidine Ph2 failure Nov 2024 | B13: $8.7B (paid) | C13: ~$5.2B implied (-$3.5B impairment) | D13: -40% | E13: Demonstrates binary Phase 2 risk in CNS. Schizophrenia muscarinic program failed despite positive Phase 1b signals.
A14: Minerva (NERV) — Ph3 failure May 2020 (roluperidone) | B14: ~$350-400M mkt cap | C14: ~$50-70M mkt cap (-81% to -86%) | D14: -81% to -86% | E14: Primary downside comp for LBRX Ph3-. Validates $100M low scenario. Eventually fell to ~$14M before $200M recapitalization.
A16: LBRX POST-PHASE 3 SCENARIO JUSTIFICATION
A18: LBRX Phase 3 Positive Scenarios
A19: Scenario | B19: Rationale | C19: Comparable Evidence
A20: Low: $1.5B (~$50/share) | B20: Conservative positive | C20: Supported by ITCI post-Ph3 bipolar data trajectory ($530M → $850M). Applied to LBRX pre-Ph3 base of $613M with a stronger rerating given schizophrenia market size. Also consistent with analyst consensus target of $44.50/share ($1.3B) BEFORE Phase 3 data.
A21: Base: $3.0B (~$100/share) | B21: Strong Phase 3 data + pipeline value | C21: Supported by Karuna pre-Ph3 trading range ($3.0-3.5B). LBRX LB-102 targets schizophrenia (same market as KarXT) with differentiated D2/D3/5-HT7 mechanism. Strong data would de-risk the asset and attract M&A interest. Also values the bipolar (ILLUMINATE-1) option.
A22: High: $5.0B (~$165/share) | B22: Karuna-style M&A premium | C22: Supported by Karuna post-EMERGENT-2 (~$5B). Requires Karuna-caliber data: robust effect size, clean safety, clear path to NDA. Represents best-case where LB-102 is viewed as best-in-class and attracts acquisition interest from large pharma.
A24: LBRX Phase 3 Negative Scenarios
A25: Scenario | B25: Rationale | C25: Comparable Evidence
A26: Low: $100M (~$3.30/share) | B26: Minerva-style wipeout | C26: Directly supported by Minerva (NERV) post-Ph3 failure: dropped from ~$400M to ~$50-70M (-86%). LBRX $100M assumes mechanism failure with minimal residual pipeline value. Aggressive downside but historically plausible.
A27: Base: $200M (~$6.60/share) | B27: Cash floor + option value | C27: LBRX has ~$400M+ cash (IPO $328M + PIPE $100M - ~$30M burn). Post-failure, stock typically trades at cash value discounted by ongoing burn rate, plus option value of surviving programs (ILLUMINATE-1 bipolar Phase 2). $200M implies ~50% discount to cash.
A28: High: $350M (~$11.50/share) | B28: Modest decline, retry potential | C28: Assumes failure is dose-related or placebo-response issue (common in CNS), not mechanism failure. Company retains cash, bipolar program intact, and market assigns modest probability of Ph3 redesign. Roughly equal to current cash position.
A30: EVECXIA POST-PHASE 2 SCENARIO JUSTIFICATION
A32: Evecxia Phase 2 Positive Scenarios
A33: Scenario | B33: Rationale | C33: Comparable Evidence
A34: Low: $800M | B34: Modest positive data | C34: Below Karuna post-Ph2 ($2B) due to: (1) Evecxia is private (30-50% liquidity discount), (2) OCD market smaller than schizophrenia, (3) 5-HTP/carbidopa less novel than KarXT muscarinic MOA. Represents statistically significant but moderate effect size.
A35: Base: $1.5B | B35: Strong data validates platform | C35: Anchored to Karuna post-Ph2 ($2B) with ~25% discount for OCD market size and private status. Assumes robust efficacy in SSRI-inadequate responders with clean safety. Would likely trigger M&A interest or IPO at premium. Also values EVX-301 (IV 5-HTP for suicidal crisis) and depression expansion.
A36: High: $3.0B | B36: Blowout data + M&A bidding war | C36: Requires exceptional circumstances: (1) transformative effect size in OCD, (2) clear signal of platform expansion (depression, PTSD, binge eating), (3) competitive M&A bidding. Comparable to Cerevel pre-acquisition ($8.7B) but Cerevel had broader pipeline. Aggressive but included for scenario completeness.
A38: Evecxia Phase 2 Negative Scenarios
A39: Scenario | B39: Rationale | C39: Comparable Evidence
A40: Low: $50M | B40: Near-total wipeout | C40: Assumes mechanism failure where 5-HTP serotonin amplification does not demonstrate clinical benefit in OCD. Company retains minimal value: cash on hand + depressed option value on EVX-301. Comparable to Minerva's eventual ~$14M nadir, though Evecxia retains private-company optionality.
A41: Base: $120M | B41: Failed primary but platform retains value | C41: Assumes OCD primary endpoint missed but secondary signals or subgroup data suggest potential. EVX-301 (suicidal crisis) retains independent value. Company can pivot to depression indication or reformulate. Represents ~4x pre-Series A value, reflecting invested capital + residual IP.
A42: High: $250M | B42: Borderline miss, dose issue, still fundable | C42: Assumes narrowly missed statistical significance (p=0.06-0.10) with clinically meaningful trends, attributable to dose selection or trial design. Investors retain confidence in mechanism. Comparable to partial-failure biotechs that maintain enough signal to raise additional capital and redesign trials.
A44: CLINICAL PROBABILITY ASSUMPTIONS
A46: P(LBRX Phase 3 Success) = 55% | B46: Industry CNS Phase 3 average: ~50-55% (BIO 2011-2020 data). LBRX LB-102 has positive Phase 2 data and differentiated MOA (D2/D3/5-HT7), supporting above-average probability. However, schizophrenia trials have high placebo response rates. 55% represents a balanced estimate at the upper end of the industry range.
A47: P(Evecxia Phase 2 Success) = 35% | B47: Industry CNS Phase 2 average: ~24% (lowest of all therapeutic areas per BIO data). Evecxia's 35% estimate is ABOVE average, justified by: (1) 5-HTP is a validated serotonin precursor with established pharmacology, (2) OCD patients with SSRI-inadequate response represent a well-defined, measurable population, (3) Phase 1 safety/target engagement data support mechanism. However, CNS Phase 2 remains inherently risky due to placebo effects and endpoint subjectivity.
A49: TAX CODE REFERENCES
A50: IRC §1202 | B50: Qualified Small Business Stock (QSBS) exclusion — 100% federal exclusion on gain from QSBS held ≥5 years (post-9/27/2010 acquisitions). Cap: greater of $10M or 10× adjusted basis.
A51: IRC §1045 | B51: Rollover of gain from QSBS to replacement QSBS within 60 days of sale. Defers gain recognition; holding period tacks from original acquisition date toward §1202 eligibility.
A52: IRC §1411 | B52: Net Investment Income Tax (NIIT) — 3.8% surtax on investment income for AGI > $200k/$250k. Applies to capital gains not excluded under §1202.
A53: IRS Publication 550 | B53: Investment Income and Expenses — guidance on capital gains, QSBS, and rollover mechanics.
A55: DATA SOURCES
A56: LBRX Stock / Financials | B56: Yahoo Finance (LBRX), SEC filings (S-1, 10-Q), Cooley IPO press release
A57: LBRX Clinical Pipeline | B57: ClinicalTrials.gov (LB-102 Phase 3, ILLUMINATE-1), GlobeNewswire corporate releases
A58: Evecxia Therapeutics | B58: Company pipeline page (evecxia.com), BioSpace financing update, BusinessWire Phase 1b dosing announcement
A59: Karuna / BMS Acquisition | B59: BMS press release (Dec 2023), BioPharma Dive, CNBC deal coverage
A60: ITCI / J&J Acquisition | B60: J&J press release (Jan 2025), BioPharma Dive, Nasdaq Phase 3 data coverage
A61: Cerevel / AbbVie Acquisition | B61: AbbVie press releases (acquisition Aug 2024, emraclidine failure Nov 2024), CNBC
A62: Minerva Phase 3 Failure | B62: GlobeNewswire results release (May 2020), Seeking Alpha (-81%), Motley Fool analysis
A63: Clinical Success Rates | B63: BIO Clinical Development Success Rates 2011-2020, CRA International "Golden Decade" report (Sep 2024), PMC/Nature studies
A65: METHODOLOGY
A66: Tax Calculations: Lot-by-lot accounting. Separate tracking of Series B QSBS basis through IPO conversion, §1045 rollover, and §1202 exclusion.
A67: QSBS Qualification: 5-year holding period calculated from original Series B close (May 3, 2022). §1045 tacking preserves holding period for Evecxia replacement stock.
A68: §1202 Exclusion Cap: Greater of $10M or 10× original adjusted basis. For $100k investment, cap = $10M (well above all scenario gains).
A69: §1045 Rollover: Deferred gain = (LBRX sale proceeds - cost basis). Basis in Evecxia = purchase price - deferred gain. Holding period tacks from original QSBS acquisition.
A70: Valuation Scenarios: Based on comparable company transactions in CNS/psychiatry (see table above). Low/Base/High represent 25th/50th/75th percentile outcomes conditional on clinical success or failure.
A71: Probability Weights: LBRX Ph3 = 55% (industry CNS Ph3 avg ~50-55%), Evecxia Ph2 = 35% (above CNS Ph2 avg of ~24%, adjusted for program-specific factors).
A72: LBRX Shares: ~30M fully diluted (post-IPO 25.3M + PIPE shares + options). Evecxia Shares at Readout: 365M estimated (post-IPO + secondary dilution).
A74: DISCLAIMER
A75: This analysis is for illustrative and educational purposes only. It does not constitute investment, tax, or legal advice. Comparable transactions cited herein are historical and do not guarantee future outcomes. Clinical trial success rates are statistical averages and individual program outcomes may vary significantly. §1045 rollovers have specific IRS requirements; state tax conformity varies. Consult a qualified CPA or tax attorney before making any investment or tax decisions.
